hydrawiser/__init__.py
hydrawiser/core.py
hydrawiser/helpers.py
Hydrawiser-0.2.dist-info/LICENSE
Hydrawiser-0.2.dist-info/METADATA
Hydrawiser-0.2.dist-info/WHEEL
Hydrawiser-0.2.dist-info/top_level.txt
Hydrawiser-0.2.dist-info/RECORD
